MANIFEST.in
README
setup.py
HMFcalc/__init__.py
HMFcalc/forms.py
HMFcalc/tasks.py
HMFcalc/tests.py
HMFcalc/utils.py
HMFcalc/views.py
HMFcalc.egg-info/PKG-INFO
HMFcalc.egg-info/SOURCES.txt
HMFcalc.egg-info/dependency_links.txt
HMFcalc.egg-info/top_level.txt
HMFcalc/templates/hmf_image_page.html
HMFcalc/templates/hmfform.html
HMFcalc/templatetags/__init__.py
HMFcalc/templatetags/hmf_version.py
HMFcalc/transfers/GiggleZ_transfer.dat
HMFcalc/transfers/Millennium_transfer.dat
HMFcalc/transfers/PLANCK_transfer.dat
HMFcalc/transfers/WMAP1_transfer.dat
HMFcalc/transfers/WMAP3_transfer.dat
HMFcalc/transfers/WMAP5_transfer.dat
HMFcalc/transfers/WMAP7_transfer.dat
HMFcalc/transfers/WMAP9_transfer.dat