Metadata-Version: 1.1
Name: HMFcalc
Version: 1.0.5
Summary: A halo mass function calculator web-app in django
Home-page: https://github.com/steven-murray/HMFcalc
Author: Steven Murray
Author-email: steven.jeanette.m@gmail.com
License: UNKNOWN
Keywords: halo mass function
Platform: UNKNOWN
Requires: numpy
Requires: pandas
